{
    "title": "CBAM_DOCUMENTO DE PREGUNTAS Y RESPUESTAS CLECAT_COMISION EUROPEA (ADU.-F- 50/24) - ATEIA ARAGÓN",
    "author": "unknown",
    "source": "ATEIA ARAGÓN",
    "date": "2024-03-12",
    "text": "Facilitamos un documento con respuestas de DG TAXUD a las consultas sobre el CBAM planteadas por CLECAT. Atentamente, Martin Fernández Secretario Técnico FETEIA Via Laietana, 32-34 4ª – 08003 Barcelona Telf:(+34)932 68 94 30| feteia@feteia.org En cumplimiento de la Ley Orgánica 3/2018 de 5 de diciembre, de Protección de Datos Personales y garantía de los derechos digitales le informamos que los datos contenidos en este correo y/o archivo adjunto formarán parte de un fichero titularidad de ATEIA ARAGON OLT con la finalidad de mantener una relación comercial. En este sentido, ATEIA ARAGON OLT se compromete a respetar la confidencialidad en la utilización de estos datos, así como a dar cumplimiento a su obligación de guardarlos y adaptar todas las medidas de seguridad oportunas para evitar su alteración, pérdida, tratamiento o acceso no autorizado. Sin perjuicio de ello, Ud. podrá ejercitar sus derechos en materia de protección de datos dirigiéndose a ateia@ateiaaragon.org. Puede ampliar esta información sobre protección de datos en nuestra web https://www.ateiaaragon.org Categorías:Boletines\n                  \n                                     0 Comentarios\n                     \n                                 0 Likes",
    "images": "https://www.ateiaaragon.org/wp-content/uploads/2016/07/LogoATEIA.png",
    "tags": "",
    "excerpt": null,
    "categories": "Boletines"
}