{
    "title": "CBAM and fertilisers: What it means to importers and exporters to the EU (The Carbon Trust Ltd)",
    "author": "System",
    "source": "Worldnewsdotcom",
    "date": "2025-02-24",
    "text": "system\nNews\nSearch\nNews\nSearch\nTop Stories\nLive\nWorld\nLocal\nCoronavirus\nBusiness\nTechnology\nSport\nEnvironment\nArts & Culture\nHealth\nSpecial Reports\nMore\nWeather\nScience\nCrime\nOpen Minds\nJournalism Review\nChat\nThursday, 10 April 2025\nLog in\nLog in\nTop Stories\nLive\nWorld\nLocal\nCoronavirus\nBusiness\nScience & Technology\nSport\nEnvironment\nArts & Culture\nHealth\nSpecial Reports\nMore\nWeather\nCrime\nOpen Minds\nJournalism Review\nChat\nArticles\nPhotos\nAdvanced Search\nCBAM and fertilisers: What it means to importers and exporters to the EU (The Carbon Trust Ltd)\nPosted\n2025-02-24",
    "images": null,
    "tags": "fertilisers knoodlsenglish noodls notfrontpage pressrelease",
    "excerpt": ") Image The EU's agricultural sector depends heavily on fertilisers to improve yields and ensure food self-sufficiency. In",
    "categories": "-"
}